mymid/__init__.py
mymid/middleware.py
query_profiling_middleware-1.0.0.dist-info/METADATA
query_profiling_middleware-1.0.0.dist-info/WHEEL
query_profiling_middleware-1.0.0.dist-info/top_level.txt
query_profiling_middleware-1.0.0.dist-info/RECORD
